{
  "log": {
    "access": "",
    "error": "",
    "loglevel": "warning"
  },
  "inbounds": [
    {
      "tag": "socks",
      "port": 1080,
      "listen": "127.0.0.1",
      "protocol": "socks",
      "sniffing": {
        "enabled": true,
        "destOverride": [
          "http",
          "tls"
        ],
        "routeOnly": false
      },
      "settings": {
        "auth": "noauth",
        "udp": true,
        "allowTransparent": false
      }
    },
    {
      "tag": "http",
      "port": 1081,
      "listen": "127.0.0.1",
      "protocol": "http",
      "sniffing": {
        "enabled": true,
        "destOverride": [
          "http",
          "tls"
        ],
        "routeOnly": false
      },
      "settings": {
        "auth": "noauth",
        "udp": true,
        "allowTransparent": false
      }
    }
  ],
  "outbounds": [
    {
      "tag": "proxy",
      "protocol": "vless",
      "settings": {
        "vnext": [
          {
            "address": "185.176.26.135",
            "port": 443,
            "users": [
              {
                "id": "66a0f35b-80fe-49c4-bbd6-39ba568dc920",
                "alterId": 0,
                "email": "t@t.tt",
                "security": "auto",
                "encryption": "none"
              }
            ]
          }
        ]
      },
      "streamSettings": {
        "network": "ws",
        "security": "tls",
        "tlsSettings": {
          "allowInsecure": false,
          "serverName": "e130917c-1b58-4136-b2d9-76dc920e0add.add97ee8-0f14-48a3-b2cd-979c56742e64.loseyourip.com",
          "fingerprint": "random",
          "show": false
        },
        "wsSettings": {
          "path": "/zgm2026.mjl.workers.dev/proxyIP=proxyip.fxxk.dedyn.io",
          "headers": {
            "Host": "e130917c-1b58-4136-b2d9-76dc920e0add.add97ee8-0f14-48a3-b2cd-979c56742e64.loseyourip.com"
          }
        }
      },
      "mux": {
        "enabled": false,
        "concurrency": -1
      }
    },
    {
      "tag": "direct",
      "protocol": "freedom",
      "settings": {}
    },
    {
      "tag": "block",
      "protocol": "blackhole",
      "settings": {
        "response": {
          "type": "http"
        }
      }
    }
  ],
  "dns": {
    "servers": [
      "1.1.1.1",
      "8.8.8.8"
    ]
  },
  "routing": {
    "domainStrategy": "AsIs",
    "rules": [
      {
        "type": "field",
        "inboundTag": [
          "api"
        ],
        "outboundTag": "api"
      },
      {
        "type": "field",
        "outboundTag": "direct",
        "domain": [
          "domain:example-example.com",
          "domain:example-example2.com"
        ]
      },
      {
        "type": "field",
        "outboundTag": "block",
        "domain": [
          "geosite:category-ads-all"
        ]
      },
      {
        "type": "field",
        "outboundTag": "direct",
        "domain": [
          "geosite:cn"
        ]
      },
      {
        "type": "field",
        "outboundTag": "direct",
        "ip": [
          "geoip:private",
          "geoip:cn"
        ]
      },
      {
        "type": "field",
        "port": "0-65535",
        "outboundTag": "proxy"
      }
    ]
  }
}